buildbot_enhanced_ui/VERSION
buildbot_enhanced_ui/__init__.py
buildbot_enhanced_ui/static/scripts.js
buildbot_enhanced_ui/static/scripts.js.map
buildbot_enhanced_ui/static/styles.css
buildbot_enhanced_ui/static/tests.js
buildbot_enhanced_ui-2021.5.26.dist-info/LICENSE
buildbot_enhanced_ui-2021.5.26.dist-info/METADATA
buildbot_enhanced_ui-2021.5.26.dist-info/WHEEL
buildbot_enhanced_ui-2021.5.26.dist-info/entry_points.txt
buildbot_enhanced_ui-2021.5.26.dist-info/top_level.txt
buildbot_enhanced_ui-2021.5.26.dist-info/RECORD
