Metadata-Version: 2.1
Name: buildbot-enhanced-ui
Version: 2021.5.26
Summary: A clearer and faster to manipulate interface for the management of BuildBot builders
Home-page: UNKNOWN
Author: Marc Leonardi
Author-email: marc@goodbarber.com
License: UNKNOWN
Platform: UNKNOWN
